miniform/__init__.py
miniform/atom.py
miniform/globals.py
miniform/imports.py
miniform/log.py
miniform/quotes.py
miniform/utils.py
miniform/version.py
miniform/assets/fonts/megamax.ttf
miniform/assets/fonts/slkscr.ttf
miniform/assets/images/icon.png
miniform/core/__init__.py
miniform/core/app/__init__.py
miniform/core/app/base.py
miniform/core/app/clock.py
miniform/core/app/events.py
miniform/core/app/inputs.py
miniform/core/app/window.py
miniform/core/process/__init__.py
miniform/core/process/camera.py
miniform/core/process/interface.py
miniform/core/process/light.py
miniform/core/process/render.py
miniform/core/process/world.py
miniform/core/resource/__init__.py
miniform/core/resource/cache.py
miniform/core/resource/interface/__init__.py
miniform/core/resource/interface/container.py
miniform/core/resource/interface/element.py
miniform/core/resource/interface/label.py
miniform/core/resource/interface/scrollview.py
miniform/core/resource/world/__init__.py
miniform/core/resource/world/grid.py
miniform/core/resource/world/light.py
miniform/core/resource/world/object.py
miniform/core/resource/world/tilemap.py
miniform/core/resource/world/world.py
miniform/core/resource/world/zone.py
miniform/scripts/__init__.py
miniform/scripts/miniforge/__init__.py
miniform/scripts/miniforge/external/.data/settings.json
miniform/scripts/miniforge/external/.data/assets/fonts/megamax.ttf
miniform/scripts/miniforge/external/.data/assets/fonts/slkscr.ttf
miniform/scripts/miniforge/external/.data/assets/images/tileset.png
miniform/scripts/miniforge/external/.data/assets/images/icon/Back.png
miniform/scripts/miniforge/external/.data/assets/images/icon/Collider.png
miniform/scripts/miniforge/external/.data/assets/images/icon/Draw.png
miniform/scripts/miniforge/external/.data/assets/images/icon/Dump.png
miniform/scripts/miniforge/external/.data/assets/images/icon/Eraser.png
miniform/scripts/miniforge/external/.data/assets/images/icon/Export.png
miniform-0.1.2.post7.dist-info/METADATA
miniform-0.1.2.post7.dist-info/WHEEL
miniform-0.1.2.post7.dist-info/entry_points.txt
miniform-0.1.2.post7.dist-info/top_level.txt
miniform-0.1.2.post7.dist-info/RECORD
