Metadata-Version: 2.4
Name: miniform
Version: 0.1.2.post7
Summary: A neat little thing... with nightly updates
Home-page: https://github.com/r3shape/miniform
Author: Izaiyah Stokes
Author-email: zafflins@gmail.com
Classifier: Programming Language :: Python :: 3.12
Classifier: License :: OSI Approved :: MIT License
Classifier: Operating System :: OS Independent
Requires-Dist: pytz
Requires-Dist: pygame-ce
Dynamic: author
Dynamic: author-email
Dynamic: classifier
Dynamic: description
Dynamic: description-content-type
Dynamic: home-page
Dynamic: requires-dist
Dynamic: summary
